clash_transer/__init__.py
clash_transer/__main__.py
clash_transer/config/__init__.py
clash_transer/downloader/__init__.py
clash_transer/downloader/session.py
clash_transer/exceptions/__init__.py
clash_transer/log/__init__.py
clash_transer/parse/__init__.py
clash_transer/parse/base64_decode.py
clash_transer/parse/emoji.py
clash_transer/parse/protocol/__init__.py
clash_transer/parse/protocol/hysteria2.py
clash_transer/parse/protocol/ss.py
clash_transer/parse/protocol/ssr.py
clash_transer/parse/protocol/vless.py
clash_transer/parse/protocol/vmess.py
clash_transer/worker/__init__.py
clash_transer/worker/detail.py
clash_transer/worker/vars.py
clash_transer-0.6.13.dist-info/METADATA
clash_transer-0.6.13.dist-info/WHEEL
clash_transer-0.6.13.dist-info/entry_points.txt
clash_transer-0.6.13.dist-info/top_level.txt
clash_transer-0.6.13.dist-info/RECORD
