Metadata-Version: 2.4
Name: clash_transer
Version: 0.6.13
Summary: 机场订阅转换工具
Home-page: 
Author: TT
Author-email: 123@mail.com
License: BSD
Keywords: clash_transer
Platform: Linux
Classifier: Programming Language :: Python :: 3.10
Classifier: Programming Language :: Python :: 3.11
Classifier: Programming Language :: Python :: 3.12
Classifier: Operating System :: POSIX :: Linux
Requires-Python: >=3.10.4
Requires-Dist: requests
Requires-Dist: PyYAML
Requires-Dist: funcy
Requires-Dist: Brotli
Requires-Dist: regex
Dynamic: author
Dynamic: author-email
Dynamic: classifier
Dynamic: description
Dynamic: description-content-type
Dynamic: keywords
Dynamic: license
Dynamic: platform
Dynamic: requires-dist
Dynamic: requires-python
Dynamic: summary
